dsagraph/__init__.py
dsagraph/dsagraph.py
dsagraph-0.0.5.dist-info/METADATA
dsagraph-0.0.5.dist-info/WHEEL
dsagraph-0.0.5.dist-info/licenses/LICENSE
dsagraph-0.0.5.dist-info/RECORD
