Metadata-Version: 2.1
Name: dsagraph
Version: 0.0.5
Summary: This is a graph library which allows user to make a graph, plot the graph and also make a adjacency list and matrix of the graph.
Project-URL: Homepage, https://github.com/Aryan-Koul29/DsaGraph
Project-URL: Bug Tracker, https://github.com/Aryan-Koul29/DsaGraph/issues
Author-email: Aryan Koul <aryankoul290301@gmail.com>, Manaswee Koli <manasweekoli@gmail.com>, Jignesh Mathure <jigmaths2487@gmail.com>, Mithun Kuthully <kuthully.mithun@gmail.com>
License-File: LICENSE
Classifier: License :: OSI Approved :: MIT License
Classifier: Operating System :: OS Independent
Classifier: Programming Language :: Python :: 3
Requires-Python: >=3.7
